kahi_minciencias_opendata_events/Kahi_minciencias_opendata_events.py
kahi_minciencias_opendata_events/__init__.py
kahi_minciencias_opendata_events/_version.py
kahi_minciencias_opendata_events/parser.py
kahi_minciencias_opendata_events/process_one.py
Kahi_minciencias_opendata_events-0.1.0b0.dist-info/METADATA
Kahi_minciencias_opendata_events-0.1.0b0.dist-info/WHEEL
Kahi_minciencias_opendata_events-0.1.0b0.dist-info/top_level.txt
Kahi_minciencias_opendata_events-0.1.0b0.dist-info/RECORD
